dcos_monitor/__init__.py
dcos_monitor/cli.py
dcos_monitor/util.py
dcos_monitor/cmds/__init__.py
dcos_monitor/cmds/cmd_dummy.py
dcos_monitor/cmds/cmd_print_full_status.py
dcos_monitor/cmds/cmd_print_marathon_apps.py
dcos_monitor/cmds/cmd_print_slave_data.py
dcos_monitor/cmds/cmd_print_state_data.py
dcos_monitor/cmds/cmd_role_data.py
dcos_monitor-0.2.0.dist-info/DESCRIPTION.rst
dcos_monitor-0.2.0.dist-info/LICENSE.txt
dcos_monitor-0.2.0.dist-info/METADATA
dcos_monitor-0.2.0.dist-info/RECORD
dcos_monitor-0.2.0.dist-info/WHEEL
dcos_monitor-0.2.0.dist-info/entry_points.txt
dcos_monitor-0.2.0.dist-info/metadata.json
dcos_monitor-0.2.0.dist-info/top_level.txt
